{
	"credit": "Made with Blockbench",
	"textures": {
		"0": "item/events/mizudeppou",
		"particle": "item/events/mizudeppou"
	},
	"elements": [
		{
			"from": [7, 4, 1],
			"to": [9, 7, 13],
			"rotation": {"angle": 0, "axis": "y", "origin": [8, 0, 7]},
			"faces": {
				"north": {"uv": [4, 0, 6, 2], "texture": "#0"},
				"east": {"uv": [4, 0, 6, 2], "texture": "#0"},
				"south": {"uv": [4, 0, 6, 2], "texture": "#0"},
				"west": {"uv": [4, 0, 6, 2], "texture": "#0"},
				"up": {"uv": [4, 0, 6, 2], "texture": "#0"},
				"down": {"uv": [4, 0, 6, 2], "texture": "#0"}
			}
		},
		{
			"from": [7.5, 5, 13],
			"to": [8.5, 6, 15],
			"rotation": {"angle": 0, "axis": "y", "origin": [8, 0, 7]},
			"faces": {
				"north": {"uv": [8, 0, 10, 2], "texture": "#0"},
				"east": {"uv": [8, 0, 10, 2], "texture": "#0"},
				"south": {"uv": [8, 0, 10, 2], "texture": "#0"},
				"west": {"uv": [8, 0, 10, 2], "texture": "#0"},
				"up": {"uv": [8, 0, 10, 2], "texture": "#0"},
				"down": {"uv": [8, 0, 10, 2], "texture": "#0"}
			}
		},
		{
			"from": [7.6, -2, 16],
			"to": [8.4, -1, 18],
			"rotation": {"angle": -45, "axis": "x", "origin": [8, 0, 7]},
			"faces": {
				"north": {"uv": [8, 0, 10, 2], "texture": "#0"},
				"east": {"uv": [8, 0, 10, 2], "texture": "#0"},
				"south": {"uv": [8, 0, 10, 2], "texture": "#0"},
				"west": {"uv": [8, 0, 10, 2], "texture": "#0"},
				"up": {"uv": [8, 0, 10, 2], "texture": "#0"},
				"down": {"uv": [8, 0, 10, 2], "texture": "#0"}
			}
		},
		{
			"from": [7.7, 6.4, 15],
			"to": [8.3, 8.4, 16],
			"rotation": {"angle": 0, "axis": "x", "origin": [8, 0, 7]},
			"faces": {
				"north": {"uv": [8, 0, 10, 2], "rotation": 180, "texture": "#0"},
				"east": {"uv": [8, 0, 10, 2], "rotation": 90, "texture": "#0"},
				"south": {"uv": [8, 0, 10, 2], "texture": "#0"},
				"west": {"uv": [8, 0, 10, 2], "rotation": 270, "texture": "#0"},
				"up": {"uv": [8, 0, 10, 2], "texture": "#0"},
				"down": {"uv": [8, 0, 10, 2], "rotation": 180, "texture": "#0"}
			}
		},
		{
			"from": [7.8, -0.4, 18],
			"to": [8.2, 1.6, 19],
			"rotation": {"angle": -45, "axis": "x", "origin": [8, 0, 7]},
			"faces": {
				"north": {"uv": [8, 0, 10, 2], "rotation": 180, "texture": "#0"},
				"east": {"uv": [8, 0, 10, 2], "rotation": 90, "texture": "#0"},
				"south": {"uv": [8, 0, 10, 2], "texture": "#0"},
				"west": {"uv": [8, 0, 10, 2], "rotation": 270, "texture": "#0"},
				"up": {"uv": [8, 0, 10, 2], "texture": "#0"},
				"down": {"uv": [8, 0, 10, 2], "rotation": 180, "texture": "#0"}
			}
		},
		{
			"from": [7.9, 8.3, 11.8],
			"to": [8.1, 9.3, 14.3],
			"rotation": {"angle": 0, "axis": "x", "origin": [8, 0, 7]},
			"faces": {
				"north": {"uv": [8, 0, 10, 2], "rotation": 180, "texture": "#0"},
				"east": {"uv": [8, 0, 10, 2], "rotation": 180, "texture": "#0"},
				"south": {"uv": [8, 0, 10, 2], "rotation": 180, "texture": "#0"},
				"west": {"uv": [8, 0, 10, 2], "rotation": 180, "texture": "#0"},
				"up": {"uv": [8, 0, 10, 2], "texture": "#0"},
				"down": {"uv": [8, 0, 10, 2], "texture": "#0"}
			}
		},
		{
			"from": [7.25, 4, 5],
			"to": [8.75, 7, 13],
			"rotation": {"angle": 45, "axis": "x", "origin": [8, 0, 7]},
			"faces": {
				"north": {"uv": [4, 0, 6, 2], "texture": "#0"},
				"east": {"uv": [4, 0, 6, 2], "texture": "#0"},
				"south": {"uv": [4, 0, 6, 2], "texture": "#0"},
				"west": {"uv": [4, 0, 6, 2], "texture": "#0"},
				"up": {"uv": [4, 0, 6, 2], "texture": "#0"},
				"down": {"uv": [4, 0, 6, 2], "texture": "#0"}
			}
		},
		{
			"from": [7.5, 3.1, 2],
			"to": [8.5, 4, 7.1],
			"rotation": {"angle": 0, "axis": "y", "origin": [8, 0, 7]},
			"faces": {
				"north": {"uv": [6, 0, 8, 2], "texture": "#0"},
				"east": {"uv": [6, 0, 8, 2], "texture": "#0"},
				"south": {"uv": [6, 0, 8, 2], "texture": "#0"},
				"west": {"uv": [6, 0, 8, 2], "texture": "#0"},
				"up": {"uv": [6, 2, 8, 0], "texture": "#0"},
				"down": {"uv": [6, 0, 8, 2], "texture": "#0"}
			}
		},
		{
			"from": [7.5, 4.6, 0],
			"to": [8.5, 6.4, 1],
			"rotation": {"angle": 0, "axis": "y", "origin": [8, 0, 7]},
			"faces": {
				"north": {"uv": [4, 0, 6, 2], "texture": "#0"},
				"east": {"uv": [4, 0, 6, 2], "texture": "#0"},
				"south": {"uv": [4, 0, 6, 2], "texture": "#0"},
				"west": {"uv": [4, 0, 6, 2], "texture": "#0"},
				"up": {"uv": [4, 0, 6, 2], "texture": "#0"},
				"down": {"uv": [4, 0, 6, 2], "texture": "#0"}
			}
		},
		{
			"from": [6.75, 7.75, 2],
			"to": [9.25, 10.25, 12],
			"rotation": {"angle": 0, "axis": "y", "origin": [8, 0, 7]},
			"faces": {
				"north": {"uv": [0, 0, 2, 2], "texture": "#0"},
				"east": {"uv": [0, 0, 2, 2], "texture": "#0"},
				"south": {"uv": [0, 0, 2, 2], "texture": "#0"},
				"west": {"uv": [0, 0, 2, 2], "texture": "#0"},
				"up": {"uv": [0, 0, 2, 2], "texture": "#0"},
				"down": {"uv": [0, 0, 2, 2], "texture": "#0"}
			}
		},
		{
			"from": [6.55, 7.55, 6],
			"to": [9.45, 10.45, 7],
			"rotation": {"angle": 0, "axis": "y", "origin": [8, 0, 7]},
			"faces": {
				"north": {"uv": [2, 0, 4, 2], "texture": "#0"},
				"east": {"uv": [2, 0, 4, 2], "texture": "#0"},
				"south": {"uv": [2, 0, 4, 2], "texture": "#0"},
				"west": {"uv": [2, 0, 4, 2], "texture": "#0"},
				"up": {"uv": [2, 0, 4, 2], "texture": "#0"},
				"down": {"uv": [2, 0, 4, 2], "texture": "#0"}
			}
		},
		{
			"from": [6.85, 3.85, 8],
			"to": [9.15, 7.15, 9],
			"rotation": {"angle": 0, "axis": "y", "origin": [8, 0, 7]},
			"faces": {
				"north": {"uv": [2, 0, 4, 2], "texture": "#0"},
				"east": {"uv": [2, 0, 4, 2], "texture": "#0"},
				"south": {"uv": [2, 0, 4, 2], "texture": "#0"},
				"west": {"uv": [2, 0, 4, 2], "texture": "#0"},
				"up": {"uv": [2, 0, 4, 2], "texture": "#0"},
				"down": {"uv": [2, 0, 4, 2], "texture": "#0"}
			}
		},
		{
			"from": [7.25, 4.65, 6.1],
			"to": [8.75, 7.55, 6.9],
			"rotation": {"angle": 0, "axis": "y", "origin": [8, 0, 7]},
			"faces": {
				"north": {"uv": [2, 0, 4, 2], "texture": "#0"},
				"east": {"uv": [2, 0, 4, 2], "texture": "#0"},
				"south": {"uv": [2, 0, 4, 2], "texture": "#0"},
				"west": {"uv": [2, 0, 4, 2], "texture": "#0"},
				"up": {"uv": [2, 0, 4, 2], "texture": "#0"},
				"down": {"uv": [2, 0, 4, 2], "texture": "#0"}
			}
		}
	],
	"display": {
		"thirdperson_righthand": {
			"translation": [0, 3.5, -3.25]
		},
		"thirdperson_lefthand": {
			"translation": [0, 3.5, -3.25]
		},
		"firstperson_righthand": {
			"translation": [0, 4.75, 0]
		},
		"firstperson_lefthand": {
			"translation": [0, 4.75, 0]
		},
		"ground": {
			"translation": [0, 7.5, 0]
		},
		"gui": {
			"rotation": [90, 45, -90],
			"translation": [1.25, 2.75, -1],
			"scale": [0.8, 0.8, 0.8]
		},
		"head": {
			"rotation": [-87.98, -41.95, -88.65],
			"translation": [-9.5, 13.5, 0]
		},
		"fixed": {
			"rotation": [90, -45, 90],
			"translation": [-2, 2.75, -1]
		}
	}
}